itk_dev_event_log/__init__.py
itk_dev_event_log-1.0.0.dist-info/licenses/LICENSE
itk_dev_event_log-1.0.0.dist-info/METADATA
itk_dev_event_log-1.0.0.dist-info/WHEEL
itk_dev_event_log-1.0.0.dist-info/top_level.txt
itk_dev_event_log-1.0.0.dist-info/RECORD
